mysql_simplelib/Database.py
mysql_simplelib/Server.py
mysql_simplelib/Table.py
mysql_simplelib/User.py
mysql_simplelib/__init__.py
mysql_simplelib/utils/__init__.py
mysql_simplelib/utils/mysql_methods.py
mysql_simplelib-0.1.dist-info/LICENSE.txt
mysql_simplelib-0.1.dist-info/METADATA
mysql_simplelib-0.1.dist-info/WHEEL
mysql_simplelib-0.1.dist-info/top_level.txt
mysql_simplelib-0.1.dist-info/RECORD
